LegacyNeuralNetworks/Fill.py
LegacyNeuralNetworks/LegacyNeuralNetworks.py
LegacyNeuralNetworks/__init__.py
LegacyNeuralNetworks/ann_fill.py
LegacyNeuralNetworks/ds_fill.py
LegacyNeuralNetworks-0.0.6.dist-info/LICENSE
LegacyNeuralNetworks-0.0.6.dist-info/METADATA
LegacyNeuralNetworks-0.0.6.dist-info/WHEEL
LegacyNeuralNetworks-0.0.6.dist-info/top_level.txt
LegacyNeuralNetworks-0.0.6.dist-info/RECORD
